sfuzzie/__init__.py
sfuzzie/fuzzer.py
sfuzzie-1.0.0.dist-info/WHEEL
sfuzzie-1.0.0.dist-info/METADATA
sfuzzie-1.0.0.dist-info/RECORD
